maddy_utils/__init__.py
maddy_utils/extend_pandas.py
maddy_utils/general_utils.py
maddy_utils/.ipynb_checkpoints/__init__-checkpoint.py
maddy_utils/.ipynb_checkpoints/extend_pandas-checkpoint.py
maddy_utils/.ipynb_checkpoints/general_utils-checkpoint.py
maddy_utils-0.0.2.dist-info/METADATA
maddy_utils-0.0.2.dist-info/WHEEL
maddy_utils-0.0.2.dist-info/licenses/LICENSE
maddy_utils-0.0.2.dist-info/RECORD
