Metadata-Version: 2.1
Name: maddy_utils
Version: 0.0.2
Summary: A package to enhance common day to day tasks in the life of a data scientist
Project-URL: Homepage, https://github.com/maddytae/my_utils
Project-URL: Bug Tracker, https://github.com/maddytae/my_utils/issues
Author-email: Madhukar Kumar Jha <madhukar.k.jha@gmail.com>
License-File: LICENSE
Classifier: License :: OSI Approved :: MIT License
Classifier: Operating System :: OS Independent
Classifier: Programming Language :: Python :: 3
Requires-Python: >=3.7
